simple_saml/__init__.py
simple_saml/admin.py
simple_saml/apps.py
simple_saml/backends.py
simple_saml/exceptions.py
simple_saml/metadata.py
simple_saml/migrations/0001_initial.py
simple_saml/migrations/0002_identityprovider_provider.py
simple_saml/migrations/__init__.py
simple_saml/models.py
simple_saml/urls.py
simple_saml/views.py
django_simple_saml-0.4.0.dist-info/METADATA
django_simple_saml-0.4.0.dist-info/WHEEL
django_simple_saml-0.4.0.dist-info/licenses/LICENSE
django_simple_saml-0.4.0.dist-info/RECORD
