Metadata-Version: 2.4
Name: django-simple-saml
Version: 0.4.0
Summary: Django app for managing multiple SAML Identity Providers.
License: MIT
License-File: LICENSE
Author: YunoJuno
Author-email: code@yunojuno.com
Maintainer: YunoJuno
Maintainer-email: code@yunojuno.com
Requires-Python: >=3.12,<4.0
Classifier: Environment :: Web Environment
Classifier: Framework :: Django
Classifier: Framework :: Django :: 5.2
Classifier: Framework :: Django :: 6.0
Classifier: License :: OSI Approved :: MIT License
Classifier: Operating System :: OS Independent
Classifier: Programming Language :: Python :: 3
Classifier: Programming Language :: Python :: 3.12
Classifier: Programming Language :: Python :: 3.13
Classifier: Programming Language :: Python :: 3.14
Classifier: Programming Language :: Python :: 3 :: Only
Provides-Extra: heroku
Provides-Extra: localhost
Requires-Dist: dj_database_url ; extra == "heroku"
Requires-Dist: django (>=5.2,<7.0)
Requires-Dist: django-sslserver ; extra == "localhost"
Requires-Dist: gunicorn ; extra == "heroku"
Requires-Dist: psycopg2-binary ; extra == "heroku"
Requires-Dist: python3-saml
Requires-Dist: social-auth-app-django
Requires-Dist: whitenoise ; extra == "heroku" or extra == "localhost"
Project-URL: Documentation, https://github.com/yunojuno/django-simple-saml
Project-URL: Homepage, https://github.com/yunojuno/django-simple-saml
Project-URL: Repository, https://github.com/yunojuno/django-simple-saml
